trillian/__init__.py
trillian-0.0.0.dist-info/METADATA
trillian-0.0.0.dist-info/WHEEL
trillian-0.0.0.dist-info/top_level.txt
trillian-0.0.0.dist-info/RECORD
